quantready_base/__init__.py
quantready_base/__main__.py
quantready_base/cli.py
quantready_base/config.py
quantready_base-0.2.2.dist-info/LICENSE
quantready_base-0.2.2.dist-info/METADATA
quantready_base-0.2.2.dist-info/WHEEL
quantready_base-0.2.2.dist-info/entry_points.txt
quantready_base-0.2.2.dist-info/RECORD
